{"frames": [

{
	"filename": "background",
	"frame": {"x":2,"y":2,"w":1280,"h":720},
	"rotated": false,
	"trimmed": false,
	"spriteSourceSize": {"x":0,"y":0,"w":1280,"h":720},
	"sourceSize": {"w":1280,"h":720}
},
{
	"filename": "circle",
	"frame": {"x":2,"y":724,"w":102,"h":102},
	"rotated": false,
	"trimmed": false,
	"spriteSourceSize": {"x":0,"y":0,"w":102,"h":102},
	"sourceSize": {"w":102,"h":102}
}],
"meta": {
	"app": "http://www.texturepacker.com",
	"version": "1.0",
	"image": "loading.png",
	"format": "RGBA8888",
	"size": {"w":2048,"h":1024},
	"scale": "1",
	"smartupdate": "$TexturePacker:SmartUpdate:ccc08c138fe84187f27f947d4c998bbc$"
}
}
